dmapp/__init__.py
dmapp/data_preprocess/__init__.py
dmapp/data_preprocess/preprocessor.py
dmapp-0.1.1.dist-info/LICENSE
dmapp-0.1.1.dist-info/METADATA
dmapp-0.1.1.dist-info/WHEEL
dmapp-0.1.1.dist-info/top_level.txt
dmapp-0.1.1.dist-info/RECORD
